{
  "project_info": {
    "project_number": "659415852807",
    "firebase_url": "https://pickupplayerapp-511be-default-rtdb.firebaseio.com",
    "project_id": "pickupplayerapp-511be",
    "storage_bucket": "pickupplayerapp-511be.appspot.com"
  },
  "client": [
    {
      "client_info": {
        "mobilesdk_app_id": "1:659415852807:android:3ac40f8e107437040cc7a2",
        "android_client_info": {
          "package_name": "com.example.pickup_player_app"
        }
      },
      "oauth_client": [
        {
          "client_id": "659415852807-jkgsnc35reud4uj0hm209hbl52570irf.apps.googleusercontent.com",
          "client_type": 3
        }
      ],
      "api_key": [
        {
          "current_key": "AIzaSyCKSLGTd-hF2d02NESvtAkTzAq_ip4BeH8"
        }
      ],
      "services": {
        "appinvite_service": {
          "other_platform_oauth_client": [
            {
              "client_id": "659415852807-jkgsnc35reud4uj0hm209hbl52570irf.apps.googleusercontent.com",
              "client_type": 3
            }
          ]
        }
      }
    }
  ],
  "configuration_version": "1"
}